<?xml version="1.0" encoding="utf-8"?><soap:Envelope xmlns:soap="http://www.w3.org/2003/05/soap-envelope" xmlns:xsi="http://www.w3.org/2001/XMLSchema-instance" xmlns:xsd="http://www.w3.org/2001/XMLSchema"><soap:Body><nfeResultMsg xmlns="http://www.portalfiscal.inf.br/nfe/wsdl/NFeAutorizacao4"><retEnviNFe versao="4.00" xmlns="http://www.portalfiscal.inf.br/nfe"><tpAmb>2</tpAmb><verAplic>SVRSnfce2602051011</verAplic><cStat>104</cStat><xMotivo>Lote processado</xMotivo><cUF>29</cUF><dhRecbto>2026-02-19T15:23:47-03:00</dhRecbto><protNFe versao="4.00"><infProt><tpAmb>2</tpAmb><verAplic>SVRSnfce2602051011</verAplic><chNFe>29260248432940000186650025253718331345058134</chNFe><dhRecbto>2026-02-19T15:23:47-03:00</dhRecbto><digVal>jhe/8HVTm8LCOrXHSq6XOCppaps=</digVal><cStat>441</cStat><xMotivo>Rejeicao: Descricao do pagamento obrigatoria para meio de pagamento 99-outros</xMotivo></infProt></protNFe></retEnviNFe></nfeResultMsg></soap:Body></soap:Envelope>